{
    "skills": [
        {
            "category": "Agile & Management",
            "items": [
                "Agile Implementation",
                "LBIP+ (Airbus Methodology)",
                "Lean Manufacturing",
                "Scrum Methodologies",
                "Kanban Framework",
                "Change Management Strategy"
            ]
        },
        {
            "category": "Tech & Digital Stack",
            "items": [
                "Python (Advanced)",
                "Java, HTML & CSS",
                "SQL & NoSQL Databases",
                "Spotfire (Data Viz)",
                "Google Apps Script",
                "Bash & DevOps",
                "Git & GitHub",
                "Jira & Confluence Admin"
            ]
        }
    ]
}